bst_plugins_experimental/__init__.py
bst_plugins_experimental/elements/__init__.py
bst_plugins_experimental/elements/bazel_build.py
bst_plugins_experimental/elements/bazel_build.yaml
bst_plugins_experimental/elements/bazelize.py
bst_plugins_experimental/elements/bazelize.yaml
bst_plugins_experimental/elements/check_forbidden.py
bst_plugins_experimental/elements/collect_integration.py
bst_plugins_experimental/elements/collect_manifest.py
bst_plugins_experimental/elements/dpkg_build.py
bst_plugins_experimental/elements/dpkg_build.yaml
bst_plugins_experimental/elements/dpkg_deploy.py
bst_plugins_experimental/elements/dpkg_deploy.yaml
bst_plugins_experimental/elements/fastboot_bootimg.py
bst_plugins_experimental/elements/fastboot_bootimg.yaml
bst_plugins_experimental/elements/fastboot_ext4.py
bst_plugins_experimental/elements/fastboot_ext4.yaml
bst_plugins_experimental/elements/flatpak_image.py
bst_plugins_experimental/elements/flatpak_image.yaml
bst_plugins_experimental/elements/flatpak_repo.py
bst_plugins_experimental/elements/flatpak_repo.yaml
bst_plugins_experimental/elements/makemaker.py
bst_plugins_experimental/elements/makemaker.yaml
bst_plugins_experimental/elements/modulebuild.py
bst_plugins_experimental/elements/modulebuild.yaml
bst_plugins_experimental/elements/oci.py
bst_plugins_experimental/elements/ostree.py
bst_plugins_experimental/elements/ostree.yaml
bst_plugins_experimental/elements/pyproject.py
bst_plugins_experimental/elements/pyproject.yaml
bst_plugins_experimental/elements/qmake.py
bst_plugins_experimental/elements/qmake.yaml
bst_plugins_experimental/elements/snap_image.py
bst_plugins_experimental/elements/snap_image.yaml
bst_plugins_experimental/elements/tar_element.py
bst_plugins_experimental/elements/tar_element.yaml
bst_plugins_experimental/elements/x86image.py
bst_plugins_experimental/elements/x86image.yaml
bst_plugins_experimental/sources/__init__.py
bst_plugins_experimental/sources/_git_utils.py
bst_plugins_experimental/sources/_utils.py
bst_plugins_experimental-1.100.1.dist-info/LICENSE
bst_plugins_experimental-1.100.1.dist-info/METADATA
bst_plugins_experimental-1.100.1.dist-info/WHEEL
bst_plugins_experimental-1.100.1.dist-info/entry_points.txt
bst_plugins_experimental-1.100.1.dist-info/top_level.txt
bst_plugins_experimental-1.100.1.dist-info/RECORD
