Metadata-Version: 2.1
Name: bst-plugins-experimental
Version: 1.100.1
Summary: A collection of experimental BuildStream plugins.
License: LGPL-2.1-or-later
Project-URL: Homepage, https://buildstream.gitlab.io/bst-plugins-experimental/
Project-URL: Documentation, https://buildstream.gitlab.io/bst-plugins-experimental/
Project-URL: Repository, https://gitlab.com/BuildStream/bst-plugins-experimental
Classifier: Programming Language :: Python :: 3
Requires-Python: >=3.7
License-File: LICENSE
Requires-Dist: packaging
Provides-Extra: bazel
Requires-Dist: requests ; extra == 'bazel'
Provides-Extra: deb
Requires-Dist: arpy ; extra == 'deb'
